caqui/__init__.py
caqui/asynchronous.py
caqui/by.py
caqui/constants.py
caqui/cssify.py
caqui/exceptions.py
caqui/helper.py
caqui/synchronous.py
caqui/easy/__init__.py
caqui/easy/action_chains.py
caqui/easy/alert.py
caqui/easy/capabilities.py
caqui/easy/drivers.py
caqui/easy/element.py
caqui/easy/server.py
caqui/easy/switch_to.py
caqui/easy/window.py
caqui-4.0.0.dist-info/licenses/LICENSE
caqui-4.0.0.dist-info/METADATA
caqui-4.0.0.dist-info/WHEEL
caqui-4.0.0.dist-info/top_level.txt
caqui-4.0.0.dist-info/RECORD
