Metadata-Version: 2.4
Name: caqui
Version: 4.0.0
Summary: Run asynchronous commands in WebDrivers
Author-email: Douglas Cardoso <noemail@noemail.com>
License: MIT License
Project-URL: Homepage, https://github.com/douglasdcm/caqui
Project-URL: Bug Tracker, https://github.com/douglasdcm/caqui/issues
Keywords: automation,asynchronous,test,crawler,robotic process automation,rpa
Classifier: Development Status :: 4 - Beta
Classifier: Programming Language :: Python :: 3
Classifier: Operating System :: OS Independent
Requires-Python: >=3.7
License-File: LICENSE
Dynamic: license-file
